dag/__init__.py
dag/exceptions.py
dag/models.py
django_dagmodel-0.1.0.dist-info/AUTHORS.rst
django_dagmodel-0.1.0.dist-info/LICENSE
django_dagmodel-0.1.0.dist-info/METADATA
django_dagmodel-0.1.0.dist-info/WHEEL
django_dagmodel-0.1.0.dist-info/top_level.txt
django_dagmodel-0.1.0.dist-info/RECORD
