Metadata-Version: 2.1
Name: django-dagmodel
Version: 0.1.0
Summary: DAG in django
Home-page: https://github.com/dryprojects/django-dagmodel
Author: dryprojects
Author-email: rk19931211@hotmail.com
License: MIT license
Keywords: dag
Platform: UNKNOWN
Classifier: Development Status :: 2 - Pre-Alpha
Classifier: Intended Audience :: Developers
Classifier: License :: OSI Approved :: MIT License
Classifier: Natural Language :: English
Classifier: Programming Language :: Python :: 3
Classifier: Programming Language :: Python :: 3.6
Classifier: Programming Language :: Python :: 3.7
Classifier: Programming Language :: Python :: 3.8
Requires-Python: >=3.6
